falcon_docs-0.4.dist-info/DESCRIPTION.rst
falcon_docs-0.4.dist-info/METADATA
falcon_docs-0.4.dist-info/RECORD
falcon_docs-0.4.dist-info/WHEEL
falcon_docs-0.4.dist-info/metadata.json
falcon_docs-0.4.dist-info/top_level.txt
falcondocs/__init__.py
falcondocs/docs.py
falcondocs/parsing.py
falcondocs/output/__init__.py
falcondocs/output/html.py
falcondocs/output/method.py
