Metadata-Version: 2.0
Name: falcon-docs
Version: 0.4
Summary: API documentation generator from docstrings, for Python's Falcon framework
Home-page: https://github.com/piotrmaslanka/falcon-docs
Author: Piotr Maślanka
Author-email: piotr.maslanka@henrietta.com.pl
License: UNKNOWN
Platform: UNKNOWN
Classifier: Programming Language :: Python
Classifier: Programming Language :: Python :: 2.7
Classifier: Programming Language :: Python :: 3.4
Classifier: Programming Language :: Python :: 3.5
Classifier: Programming Language :: Python :: Implementation :: CPython
Classifier: Programming Language :: Python :: Implementation :: PyPy
Classifier: Operating System :: OS Independent
Classifier: Development Status :: 3 - Alpha
Classifier: License :: OSI Approved :: MIT License
Classifier: Topic :: Software Development :: Libraries
Requires-Dist: falcon
Requires-Dist: markdown2
Requires-Dist: six
